seleniumX/__init__.py
seleniumX/randomizer.py
seleniumX/scraper.py
seleniumx-0.1.1.dist-info/LICENSE.txt
seleniumx-0.1.1.dist-info/METADATA
seleniumx-0.1.1.dist-info/WHEEL
seleniumx-0.1.1.dist-info/top_level.txt
seleniumx-0.1.1.dist-info/RECORD
