Metadata-Version: 2.1
Name: seleniumx
Version: 0.1.1
Summary: Selenium extension
Home-page: https://github.com/GrilledChickenThighs/seleniumX
Author: Paul D. Mendes
Author-email: pauldmendes@yahoo.com
License: MIT
Platform: UNKNOWN
Classifier: License :: OSI Approved :: MIT License
Classifier: Programming Language :: Python
Classifier: Programming Language :: Python :: 3
Classifier: Programming Language :: Python :: 3.6
Classifier: Programming Language :: Python :: Implementation :: CPython
Classifier: Programming Language :: Python :: Implementation :: PyPy
Requires-Python: >=3.6.0
Requires-Dist: webdriver-manager (==2.2.0)
Requires-Dist: selenium (==3.141.0)
